tawazi/__init__.py
tawazi/_decorators.py
tawazi/_helpers.py
tawazi/_object_helpers.py
tawazi/config.py
tawazi/consts.py
tawazi/errors.py
tawazi/profile.py
tawazi/py.typed
tawazi/_dag/__init__.py
tawazi/_dag/constructor.py
tawazi/_dag/dag.py
tawazi/_dag/digraph.py
tawazi/_dag/helpers.py
tawazi/node/__init__.py
tawazi/node/extend.py
tawazi/node/functions.py
tawazi/node/helpers.py
tawazi/node/node.py
tawazi/node/uxn.py
tawazi-0.6.2.dist-info/LICENSE
tawazi-0.6.2.dist-info/WHEEL
tawazi-0.6.2.dist-info/METADATA
tawazi-0.6.2.dist-info/RECORD
