Metadata-Version: 2.1
Name: tawazi
Version: 0.6.2
Summary: This library helps you execute a set of functions in a Directed Acyclic Graph (DAG) dependency structure in parallel in a production environment.
Author-email: Mindee <contact@mindee.com>
Maintainer: Bashir Abdel Wahed, Matthias Cremieux
Requires-Python: >=3.9,<4
Requires-Dist: networkx>=2,<4
Requires-Dist: pydantic
Requires-Dist: PyYaml>=6
Requires-Dist: typing_extensions>=4.4.0
Requires-Dist: packaging
Requires-Dist: numpy ; extra == "dev"
Requires-Dist: pytest>=7.1.2 ; extra == "dev"
Requires-Dist: pytest-asyncio ; extra == "dev"
Requires-Dist: pytest-mock ; extra == "dev"
Requires-Dist: pytest-cov>=4.0.0 ; extra == "dev"
Requires-Dist: pytest-codeblocks ; extra == "dev"
Requires-Dist: pre-commit ; extra == "dev"
Requires-Dist: multiprocessing_on_dill ; extra == "dev"
Requires-Dist: pathos ; extra == "dev"
Requires-Dist: mkdocs>=1.4.0 ; extra == "doc"
Requires-Dist: mike==1.1.2 ; extra == "doc"
Requires-Dist: mkdocs-exclude==1.0.2 ; extra == "doc"
Requires-Dist: mkdocs-material==9.2.6 ; extra == "doc"
Requires-Dist: mkdocstrings-python ; extra == "doc"
Requires-Dist: graphviz ; extra == "graphviz"
Requires-Dist: pydantic>=1.0.0,<2 ; extra == "pydantic1"
Provides-Extra: dev
Provides-Extra: doc
Provides-Extra: graphviz
Provides-Extra: pydantic1
